configure_with_sudo/__about__.py
configure_with_sudo/__init__.py
configure_with_sudo/configure_with_sudo.py
configure_with_sudo/version.py
configure_with_sudo/config/default.yaml
configure_with_sudo-0.1.1.dist-info/LICENSE
configure_with_sudo-0.1.1.dist-info/METADATA
configure_with_sudo-0.1.1.dist-info/WHEEL
configure_with_sudo-0.1.1.dist-info/top_level.txt
configure_with_sudo-0.1.1.dist-info/RECORD
