Metadata-Version: 2.1
Name: configure_with_sudo
Version: 0.1.1
Summary: A Python class to handle executing system commands using sudo
Home-page: https://github.com/zcutlip/configure-with-sudo
Author: Zachary Cutlip
Author-email: uid000@gmail.com
License: MIT
Requires-Python: >=2.7
License-File: LICENSE
